printolog/__init__.py
printolog/decorator.py
printolog-0.1.dist-info/METADATA
printolog-0.1.dist-info/WHEEL
printolog-0.1.dist-info/top_level.txt
printolog-0.1.dist-info/RECORD
